checkmysql/__init__.py
checkmysql/cli.py
checkmysql/connector.py
test/__init__.py
test/mysql-check.py
checkmysql-0.1.9.dist-info/LICENSE
checkmysql-0.1.9.dist-info/METADATA
checkmysql-0.1.9.dist-info/WHEEL
checkmysql-0.1.9.dist-info/entry_points.txt
checkmysql-0.1.9.dist-info/top_level.txt
checkmysql-0.1.9.dist-info/RECORD
