Metadata-Version: 2.1
Name: checkmysql
Version: 0.1.9
Summary: Check MySQL cli interface
Home-page: https://github.com/gni/checkmysql
Author: Lucian BLETAN
Author-email: neuraluc@gmail.com
License: BSD
Platform: any
Classifier: Development Status :: 4 - Beta
Classifier: Environment :: Console
Classifier: Intended Audience :: Developers
Classifier: License :: OSI Approved :: BSD License
Classifier: Operating System :: POSIX
Classifier: Operating System :: MacOS
Classifier: Operating System :: Unix
Classifier: Programming Language :: Python
Classifier: Programming Language :: Python :: 2
Classifier: Programming Language :: Python :: 3
Classifier: Topic :: Software Development :: Libraries :: Python Modules
License-File: LICENSE
Requires-Dist: typer
Requires-Dist: PyMySQL
Requires-Dist: rich
